pantsbuild.pants.testinfra-1.25.0-py3.6-nspkg.pth
pants_test/console_rule_test_base.py
pants_test/deprecated_testinfra.py
pants_test/interpreter_selection_utils.py
pants_test/pants_run_integration_test.py
pants_test/task_test_base.py
pants_test/test_base.py
pants_test/base/__init__.py
pants_test/base/context_utils.py
pants_test/engine/__init__.py
pants_test/engine/base_engine_test.py
pants_test/engine/util.py
pants_test/jvm/__init__.py
pants_test/jvm/jar_task_test_base.py
pants_test/jvm/jvm_tool_task_test_base.py
pants_test/jvm/nailgun_task_test_base.py
pants_test/option/util/__init__.py
pants_test/option/util/fakes.py
pants_test/subsystem/__init__.py
pants_test/subsystem/subsystem_util.py
pants_test/testutils/__init__.py
pants_test/testutils/file_test_util.py
pantsbuild.pants.testinfra-1.25.0.dist-info/METADATA
pantsbuild.pants.testinfra-1.25.0.dist-info/RECORD
pantsbuild.pants.testinfra-1.25.0.dist-info/WHEEL
pantsbuild.pants.testinfra-1.25.0.dist-info/namespace_packages.txt
pantsbuild.pants.testinfra-1.25.0.dist-info/top_level.txt
pantsbuild.pants.testinfra-1.25.0.dist-info/zip-safe
